{
  "id": "19807c7e718181c9",
  "subject": "Bitcoin Hit $160,000 by Year-End? Our CNBC Interview Explains",
  "from": "10x Research <hi@update.10xresearch.com>",
  "date": "Mon, 14 Jul 2025 07:13:16 +0000 (UTC)",
  "body": "[On December 16, 2024](http://ation-ceremony), we set our end-2025 Bitcoin target at $160,000. At the time, it sounded ambitious—and it still does—given the scale of capital required to reach that level. Yet, based on recent developments, it remains within reach. For more context and insight, check out our latest interview on CNBC.\r\n\r\nBitcoin could hit $160,000 by end-2025: Expert: (https://www.cnbc.com/video/2025/07/14/bitcoin-could-hit-160000-by-end-2025-expert.html)\r\n\r\nView image: (https://media.beehiiv.com/cdn-cgi/image/fit=scale-down,format=auto,onerror=redirect,quality=80/uploads/asset/file/829d685f-3781-414a-adf2-822447709f1a/image.png?t=1752476797)\r\nCaption: \r\n\r\nView image: (https://media.beehiiv.com/cdn-cgi/image/fit=scale-down,format=auto,onerror=redirect,quality=80/uploads/asset/file/ed45c751-e1de-4953-87bf-7f269bf9e5ff/image.png?t=1752476391)\r\nFollow image link: (https://www.cnbc.com/video/2025/07/14/bitcoin-could-hit-160000-by-end-2025-expert.html)\r\nCaption: \r\n\r\nView image: (https://media.beehiiv.com/cdn-cgi/image/fit=scale-down,format=auto,onerror=redirect,quality=80/uploads/asset/file/691cb6e1-da82-4efa-9dab-2cb32b3d02c3/image.png?t=1752476876)\r\nFollow image link: (https://cointelegraph.com/news/bitcoin-rally-fueled-us-deficit-fiscal-concern)\r\nCaption: \r\n\r\nBitcoin is rallying on US deficit concerns, not hype: Analyst: (https://cointelegraph.com/news/bitcoin-rally-fueled-us-deficit-fiscal-concern)\r\n\r\n\r\n———\r\n\r\nYou are reading a plain text version of this post. For the best experience, copy and paste this link in your browser to view the post online:\r\nhttps://update.10xresearch.com/p/bitcoin-hit-160-000-by-year-end-our-cnbc-interview-explains-6ef2\r\n"
}