[
  {
    "title": "10x Research Claims Success in Predicting Bitcoin Corrections and Coinbase Short",
    "summary": "Investment research firm 10x Research claims to have successfully predicted all three major Bitcoin corrections in 2025 and profited from shorting Coinbase stock. The firm is promoting their premium subscription service after Coinbase dropped 17% following earnings miss.",
    "categories": [
      "market",
      "institutional"
    ],
    "importance": "low",
    "primary_link": "https://update.10xresearch.com/upgrade",
    "additional_links": [],
    "images": [
      "https://media.beehiiv.com/cdn-cgi/image/fit=scale-down,format=auto,onerror=redirect,quality=80/uploads/asset/file/24e503e4-f019-48f8-8b17-108fd6113d6f/image.png?t=1754106366"
    ],
    "source": "10x Research <hi@update.10xresearch.com>",
    "emailDate": "Sat, 02 Aug 2025 03:53:56 +0000 (UTC)"
  }
]